{
  "node": {
    "00273fad059a5384851b45163053c0131b3e07fc01": {
      "workers": {
        "app/[locale]/(admin)/admin/roles/[id]/edit/page": {
          "moduleId": 340055,
          "async": true,
          "exportedName": "getClientIp",
          "filename": "src/shared/lib/ip.ts"
        }
      },
      "layer": {
        "app/[locale]/(admin)/admin/roles/[id]/edit/page": "rsc"
      },
      "exportedName": "getClientIp",
      "filename": "src/shared/lib/ip.ts"
    },
    "6099c8b643c5a38cf1989bec4276b81cd945be57ae": {
      "workers": {
        "app/[locale]/(admin)/admin/roles/[id]/edit/page": {
          "moduleId": 340055,
          "async": true,
          "exportedName": "$$RSC_SERVER_ACTION_0",
          "filename": "src/app/[locale]/(admin)/admin/roles/[id]/edit/page.tsx"
        }
      },
      "layer": {
        "app/[locale]/(admin)/admin/roles/[id]/edit/page": "rsc"
      },
      "exportedName": "$$RSC_SERVER_ACTION_0",
      "filename": "src/app/[locale]/(admin)/admin/roles/[id]/edit/page.tsx"
    }
  },
  "edge": {}
}