{
  "node": {
    "60f02550c56638bf066ca3dfed46dbc7d49940c6eb": {
      "workers": {
        "app/[locale]/(landing)/settings/security/page": {
          "moduleId": 898895,
          "async": true,
          "exportedName": "$$RSC_SERVER_ACTION_0",
          "filename": "src/app/[locale]/(landing)/settings/security/page.tsx"
        }
      },
      "layer": {
        "app/[locale]/(landing)/settings/security/page": "rsc"
      },
      "exportedName": "$$RSC_SERVER_ACTION_0",
      "filename": "src/app/[locale]/(landing)/settings/security/page.tsx"
    },
    "00cf3b2c537f0cc1f944b88c7919b6b67ef0f6d736": {
      "workers": {
        "app/[locale]/(landing)/settings/security/page": {
          "moduleId": 898895,
          "async": true,
          "exportedName": "getClientIp",
          "filename": "src/shared/lib/ip.ts"
        }
      },
      "layer": {
        "app/[locale]/(landing)/settings/security/page": "rsc"
      },
      "exportedName": "getClientIp",
      "filename": "src/shared/lib/ip.ts"
    }
  },
  "edge": {}
}